ampel/argo/api.py
ampel/argo/app.py
ampel/argo/auth.py
ampel/argo/job.py
ampel/argo/models.py
ampel/argo/settings.py
ampel_argo-0.3.0a1.dist-info/WHEEL
ampel_argo-0.3.0a1.dist-info/entry_points.txt
ampel_argo-0.3.0a1.dist-info/METADATA
ampel_argo-0.3.0a1.dist-info/RECORD
